vis_wizard/__init__.py
vis_wizard/eda/__init__.py
vis_wizard/eda/histogram.py
vis_wizard-0.1.2.dist-info/licenses/LICENSE
vis_wizard-0.1.2.dist-info/METADATA
vis_wizard-0.1.2.dist-info/WHEEL
vis_wizard-0.1.2.dist-info/top_level.txt
vis_wizard-0.1.2.dist-info/RECORD
